{"note":"This file is an internal implementation detail to speed up HTML report generation. Its format can change at any time. You might be looking for the JSON report: https://coverage.rtfd.io/cmd.html#cmd-json","format":5,"version":"7.13.5","globals":"7342c1a6ed7302c74b71f0f15027d467","files":{"z_91c4189ccc277042___init___py":{"hash":"5142eaadc3d21ab8176502a9f6ad377a","index":{"url":"z_91c4189ccc277042___init___py.html","file":"src/gitversioned/__init__.py","description":"","nums":{"precision":0,"n_files":1,"n_statements":8,"n_excluded":0,"n_missing":0,"n_branches":0,"n_partial_branches":0,"n_missing_branches":0}}},"z_91c4189ccc277042_compat_py":{"hash":"75da895fda4f4a96c0d92a638f2f0c5a","index":{"url":"z_91c4189ccc277042_compat_py.html","file":"src/gitversioned/compat.py","description":"","nums":{"precision":0,"n_files":1,"n_statements":22,"n_excluded":0,"n_missing":5,"n_branches":0,"n_partial_branches":0,"n_missing_branches":0}}},"z_91c4189ccc277042_logging_py":{"hash":"8355ffe5af1517a4da20063e08f8a923","index":{"url":"z_91c4189ccc277042_logging_py.html","file":"src/gitversioned/logging.py","description":"","nums":{"precision":0,"n_files":1,"n_statements":55,"n_excluded":0,"n_missing":15,"n_branches":0,"n_partial_branches":0,"n_missing_branches":0}}},"z_a3cc2b5087ff051c___init___py":{"hash":"9ac6a8e07be29595e5afbcb111e3a901","index":{"url":"z_a3cc2b5087ff051c___init___py.html","file":"src/gitversioned/plugins/__init__.py","description":"","nums":{"precision":0,"n_files":1,"n_statements":0,"n_excluded":0,"n_missing":0,"n_branches":0,"n_partial_branches":0,"n_missing_branches":0}}},"z_a3cc2b5087ff051c_hatchling_plugin_py":{"hash":"96a2ddb4ed5f55d7a699a42f95fcf515","index":{"url":"z_a3cc2b5087ff051c_hatchling_plugin_py.html","file":"src/gitversioned/plugins/hatchling_plugin.py","description":"","nums":{"precision":0,"n_files":1,"n_statements":68,"n_excluded":0,"n_missing":14,"n_branches":0,"n_partial_branches":0,"n_missing_branches":0}}},"z_a3cc2b5087ff051c_setuptools_plugin_py":{"hash":"c5642b0e1cb3512be0e4d9bba7dc4b16","index":{"url":"z_a3cc2b5087ff051c_setuptools_plugin_py.html","file":"src/gitversioned/plugins/setuptools_plugin.py","description":"","nums":{"precision":0,"n_files":1,"n_statements":134,"n_excluded":0,"n_missing":27,"n_branches":0,"n_partial_branches":0,"n_missing_branches":0}}},"z_91c4189ccc277042_settings_py":{"hash":"576cb71ce6bb4e89e14a535236de2e67","index":{"url":"z_91c4189ccc277042_settings_py.html","file":"src/gitversioned/settings.py","description":"","nums":{"precision":0,"n_files":1,"n_statements":56,"n_excluded":0,"n_missing":7,"n_branches":0,"n_partial_branches":0,"n_missing_branches":0}}},"z_faedbe6e48ce5080___init___py":{"hash":"4c205f9d7313819529b63a7841c99c1b","index":{"url":"z_faedbe6e48ce5080___init___py.html","file":"src/gitversioned/utils/__init__.py","description":"","nums":{"precision":0,"n_files":1,"n_statements":5,"n_excluded":0,"n_missing":0,"n_branches":0,"n_partial_branches":0,"n_missing_branches":0}}},"z_faedbe6e48ce5080_environment_py":{"hash":"dab20c7c6745ff86934f304f9232b785","index":{"url":"z_faedbe6e48ce5080_environment_py.html","file":"src/gitversioned/utils/environment.py","description":"","nums":{"precision":0,"n_files":1,"n_statements":51,"n_excluded":0,"n_missing":5,"n_branches":0,"n_partial_branches":0,"n_missing_branches":0}}},"z_faedbe6e48ce5080_git_py":{"hash":"afa0a70f7f3b6eeb8767d6bfc9fbff79","index":{"url":"z_faedbe6e48ce5080_git_py.html","file":"src/gitversioned/utils/git.py","description":"","nums":{"precision":0,"n_files":1,"n_statements":141,"n_excluded":0,"n_missing":13,"n_branches":0,"n_partial_branches":0,"n_missing_branches":0}}},"z_faedbe6e48ce5080_pydantic_py":{"hash":"82d74079e582d209ea4677f96e805721","index":{"url":"z_faedbe6e48ce5080_pydantic_py.html","file":"src/gitversioned/utils/pydantic.py","description":"","nums":{"precision":0,"n_files":1,"n_statements":48,"n_excluded":0,"n_missing":12,"n_branches":0,"n_partial_branches":0,"n_missing_branches":0}}},"z_91c4189ccc277042_versioning_py":{"hash":"f541fb647dafd8b572f7f2ca83aa188c","index":{"url":"z_91c4189ccc277042_versioning_py.html","file":"src/gitversioned/versioning.py","description":"","nums":{"precision":0,"n_files":1,"n_statements":210,"n_excluded":0,"n_missing":56,"n_branches":0,"n_partial_branches":0,"n_missing_branches":0}}}}}